{".class": "MypyFile", "_fullname": "libcst._parser.parso.pgen2.grammar_parser", "future_import_flags": [], "is_partial_stub_package": false, "is_stub": false, "names": {".class": "SymbolTable", "Generator": {".class": "SymbolTableNode", "cross_ref": "typing.Generator", "kind": "Gdef"}, "GrammarParser": {".class": "SymbolTableNode", "kind": "Gdef", "node": {".class": "TypeInfo", "_promote": null, "abstract_attributes": [], "bases": ["builtins.object"], "declared_metaclass": null, "defn": {".class": "ClassDef", "fullname": "libcst._parser.parso.pgen2.grammar_parser.GrammarParser", "name": "GrammarParser", "type_vars": []}, "deletable_attributes": [], "flags": [], "fullname": "libcst._parser.parso.pgen2.grammar_parser.GrammarParser", "has_param_spec_type": false, "metaclass_type": null, "metadata": {}, "module_name": "libcst._parser.parso.pgen2.grammar_parser", "mro": ["libcst._parser.parso.pgen2.grammar_parser.GrammarParser", "builtins.object"], "names": {".class": "SymbolTable", "__init__": {".class": "SymbolTableNode", "kind": "Mdef", "node": {".class": "FuncDef", "arg_kinds": [0, 0], "arg_names": ["self", "bnf_grammar"], "flags": [], "fullname": "libcst._parser.parso.pgen2.grammar_parser.GrammarParser.__init__", "name": "__init__", "type": {".class": "CallableType", "arg_kinds": [0, 0], "arg_names": ["self", "bnf_grammar"], "arg_types": ["libcst._parser.parso.pgen2.grammar_parser.GrammarParser", "builtins.str"], "bound_args": [], "def_extras": {"first_arg": "self"}, "fallback": "builtins.function", "from_concatenate": false, "implicit": false, "is_ellipsis_args": false, "name": "__init__ of GrammarParser", "ret_type": {".class": "NoneType"}, "type_guard": null, "variables": []}}}, "_bnf_grammar": {".class": "SymbolTableNode", "implicit": true, "kind": "Mdef", "node": {".class": "Var", "flags": ["explicit_self_type", "is_ready"], "fullname": "libcst._parser.parso.pgen2.grammar_parser.GrammarParser._bnf_grammar", "name": "_bnf_grammar", "type": "builtins.str"}}, "_current_rule_name": {".class": "SymbolTableNode", "implicit": true, "kind": "Mdef", "node": {".class": "Var", "flags": [], "fullname": "libcst._parser.parso.pgen2.grammar_parser.GrammarParser._current_rule_name", "name": "_current_rule_name", "type": {".class": "AnyType", "missing_import_name": null, "source_any": null, "type_of_any": 1}}}, "_expect": {".class": "SymbolTableNode", "kind": "Mdef", "node": {".class": "FuncDef", "arg_kinds": [0, 0, 1], "arg_names": ["self", "type_", "value"], "flags": [], "fullname": "libcst._parser.parso.pgen2.grammar_parser.GrammarParser._expect", "name": "_expect", "type": null}}, "_gettoken": {".class": "SymbolTableNode", "kind": "Mdef", "node": {".class": "FuncDef", "arg_kinds": [0], "arg_names": ["self"], "flags": [], "fullname": "libcst._parser.parso.pgen2.grammar_parser.GrammarParser._gettoken", "name": "_gettoken", "type": {".class": "CallableType", "arg_kinds": [0], "arg_names": ["self"], "arg_types": ["libcst._parser.parso.pgen2.grammar_parser.GrammarParser"], "bound_args": [], "def_extras": {"first_arg": "self"}, "fallback": "builtins.function", "from_concatenate": false, "implicit": false, "is_ellipsis_args": false, "name": "_gettoken of GrammarParser", "ret_type": {".class": "NoneType"}, "type_guard": null, "variables": []}}}, "_parse_atom": {".class": "SymbolTableNode", "kind": "Mdef", "node": {".class": "FuncDef", "arg_kinds": [0], "arg_names": ["self"], "flags": [], "fullname": "libcst._parser.parso.pgen2.grammar_parser.GrammarParser._parse_atom", "name": "_parse_atom", "type": null}}, "_parse_item": {".class": "SymbolTableNode", "kind": "Mdef", "node": {".class": "FuncDef", "arg_kinds": [0], "arg_names": ["self"], "flags": [], "fullname": "libcst._parser.parso.pgen2.grammar_parser.GrammarParser._parse_item", "name": "_parse_item", "type": null}}, "_parse_items": {".class": "SymbolTableNode", "kind": "Mdef", "node": {".class": "FuncDef", "arg_kinds": [0], "arg_names": ["self"], "flags": [], "fullname": "libcst._parser.parso.pgen2.grammar_parser.GrammarParser._parse_items", "name": "_parse_items", "type": null}}, "_parse_rhs": {".class": "SymbolTableNode", "kind": "Mdef", "node": {".class": "FuncDef", "arg_kinds": [0], "arg_names": ["self"], "flags": [], "fullname": "libcst._parser.parso.pgen2.grammar_parser.GrammarParser._parse_rhs", "name": "_parse_rhs", "type": null}}, "_raise_error": {".class": "SymbolTableNode", "kind": "Mdef", "node": {".class": "FuncDef", "arg_kinds": [0, 0, 2], "arg_names": ["self", "msg", "args"], "flags": [], "fullname": "libcst._parser.parso.pgen2.grammar_parser.GrammarParser._raise_error", "name": "_raise_error", "type": {".class": "CallableType", "arg_kinds": [0, 0, 2], "arg_names": ["self", "msg", "args"], "arg_types": ["libcst._parser.parso.pgen2.grammar_parser.GrammarParser", "builtins.str", "builtins.object"], "bound_args": [], "def_extras": {"first_arg": "self"}, "fallback": "builtins.function", "from_concatenate": false, "implicit": false, "is_ellipsis_args": false, "name": "_raise_error of GrammarParser", "ret_type": {".class": "NoneType"}, "type_guard": null, "variables": []}}}, "begin": {".class": "SymbolTableNode", "implicit": true, "kind": "Mdef", "node": {".class": "Var", "flags": [], "fullname": "libcst._parser.parso.pgen2.grammar_parser.GrammarParser.begin", "name": "begin", "type": {".class": "AnyType", "missing_import_name": null, "source_any": null, "type_of_any": 1}}}, "generator": {".class": "SymbolTableNode", "implicit": true, "kind": "Mdef", "node": {".class": "Var", "flags": [], "fullname": "libcst._parser.parso.pgen2.grammar_parser.GrammarParser.generator", "name": "generator", "type": {".class": "Instance", "args": [{".class": "TupleType", "implicit": false, "items": [{".class": "AnyType", "missing_import_name": null, "source_any": null, "type_of_any": 1}, {".class": "AnyType", "missing_import_name": null, "source_any": null, "type_of_any": 1}, {".class": "AnyType", "missing_import_name": null, "source_any": null, "type_of_any": 1}, {".class": "AnyType", "missing_import_name": null, "source_any": null, "type_of_any": 1}], "partial_fallback": "libcst._parser.parso.python.tokenize.PythonToken"}, {".class": "NoneType"}, {".class": "NoneType"}], "type_ref": "typing.Generator"}}}, "parse": {".class": "SymbolTableNode", "kind": "Mdef", "node": {".class": "FuncDef", "arg_kinds": [0], "arg_names": ["self"], "flags": ["is_generator"], "fullname": "libcst._parser.parso.pgen2.grammar_parser.GrammarParser.parse", "name": "parse", "type": {".class": "CallableType", "arg_kinds": [0], "arg_names": ["self"], "arg_types": ["libcst._parser.parso.pgen2.grammar_parser.GrammarParser"], "bound_args": [], "def_extras": {"first_arg": "self"}, "fallback": "builtins.function", "from_concatenate": false, "implicit": false, "is_ellipsis_args": false, "name": "parse of GrammarParser", "ret_type": {".class": "Instance", "args": [{".class": "TupleType", "implicit": false, "items": ["libcst._parser.parso.pgen2.grammar_parser.NFAState", "libcst._parser.parso.pgen2.grammar_parser.NFAState"], "partial_fallback": {".class": "Instance", "args": [{".class": "AnyType", "missing_import_name": null, "source_any": null, "type_of_any": 6}], "type_ref": "builtins.tuple"}}, {".class": "NoneType"}, {".class": "NoneType"}], "type_ref": "typing.Generator"}, "type_guard": null, "variables": []}}}, "type": {".class": "SymbolTableNode", "implicit": true, "kind": "Mdef", "node": {".class": "Var", "flags": [], "fullname": "libcst._parser.parso.pgen2.grammar_parser.GrammarParser.type", "name": "type", "type": {".class": "AnyType", "missing_import_name": null, "source_any": null, "type_of_any": 1}}}, "value": {".class": "SymbolTableNode", "implicit": true, "kind": "Mdef", "node": {".class": "Var", "flags": [], "fullname": "libcst._parser.parso.pgen2.grammar_parser.GrammarParser.value", "name": "value", "type": {".class": "AnyType", "missing_import_name": null, "source_any": null, "type_of_any": 1}}}}, "slots": null, "tuple_type": null, "type_vars": [], "typeddict_type": null}}, "List": {".class": "SymbolTableNode", "cross_ref": "typing.List", "kind": "Gdef"}, "NFAArc": {".class": "SymbolTableNode", "kind": "Gdef", "node": {".class": "TypeInfo", "_promote": null, "abstract_attributes": [], "bases": ["builtins.object"], "declared_metaclass": null, "defn": {".class": "ClassDef", "fullname": "libcst._parser.parso.pgen2.grammar_parser.NFAArc", "name": "NFAArc", "type_vars": []}, "deletable_attributes": [], "flags": [], "fullname": "libcst._parser.parso.pgen2.grammar_parser.NFAArc", "has_param_spec_type": false, "metaclass_type": null, "metadata": {}, "module_name": "libcst._parser.parso.pgen2.grammar_parser", "mro": ["libcst._parser.parso.pgen2.grammar_parser.NFAArc", "builtins.object"], "names": {".class": "SymbolTable", "__init__": {".class": "SymbolTableNode", "kind": "Mdef", "node": {".class": "FuncDef", "arg_kinds": [0, 0, 0], "arg_names": ["self", "next_", "nonterminal_or_string"], "flags": [], "fullname": "libcst._parser.parso.pgen2.grammar_parser.NFAArc.__init__", "name": "__init__", "type": {".class": "CallableType", "arg_kinds": [0, 0, 0], "arg_names": ["self", "next_", "nonterminal_or_string"], "arg_types": ["libcst._parser.parso.pgen2.grammar_parser.NFAArc", "libcst._parser.parso.pgen2.grammar_parser.NFAState", {".class": "UnionType", "items": ["builtins.str", {".class": "NoneType"}]}], "bound_args": [], "def_extras": {"first_arg": "self"}, "fallback": "builtins.function", "from_concatenate": false, "implicit": false, "is_ellipsis_args": false, "name": "__init__ of NFAArc", "ret_type": {".class": "NoneType"}, "type_guard": null, "variables": []}}}, "__repr__": {".class": "SymbolTableNode", "kind": "Mdef", "node": {".class": "FuncDef", "arg_kinds": [0], "arg_names": [null], "flags": [], "fullname": "libcst._parser.parso.pgen2.grammar_parser.NFAArc.__repr__", "name": "__repr__", "type": {".class": "CallableType", "arg_kinds": [0], "arg_names": [null], "arg_types": ["libcst._parser.parso.pgen2.grammar_parser.NFAArc"], "bound_args": [], "def_extras": {"first_arg": "self"}, "fallback": "builtins.function", "from_concatenate": false, "implicit": false, "is_ellipsis_args": false, "name": "__repr__ of NFAArc", "ret_type": "builtins.str", "type_guard": null, "variables": []}}}, "next": {".class": "SymbolTableNode", "implicit": true, "kind": "Mdef", "node": {".class": "Var", "flags": ["explicit_self_type", "is_ready"], "fullname": "libcst._parser.parso.pgen2.grammar_parser.NFAArc.next", "name": "next", "type": "libcst._parser.parso.pgen2.grammar_parser.NFAState"}}, "nonterminal_or_string": {".class": "SymbolTableNode", "implicit": true, "kind": "Mdef", "node": {".class": "Var", "flags": ["explicit_self_type", "is_ready"], "fullname": "libcst._parser.parso.pgen2.grammar_parser.NFAArc.nonterminal_or_string", "name": "nonterminal_or_string", "type": {".class": "UnionType", "items": ["builtins.str", {".class": "NoneType"}]}}}}, "slots": null, "tuple_type": null, "type_vars": [], "typeddict_type": null}}, "NFAState": {".class": "SymbolTableNode", "kind": "Gdef", "node": {".class": "TypeInfo", "_promote": null, "abstract_attributes": [], "bases": ["builtins.object"], "declared_metaclass": null, "defn": {".class": "ClassDef", "fullname": "libcst._parser.parso.pgen2.grammar_parser.NFAState", "name": "NFAState", "type_vars": []}, "deletable_attributes": [], "flags": [], "fullname": "libcst._parser.parso.pgen2.grammar_parser.NFAState", "has_param_spec_type": false, "metaclass_type": null, "metadata": {}, "module_name": "libcst._parser.parso.pgen2.grammar_parser", "mro": ["libcst._parser.parso.pgen2.grammar_parser.NFAState", "builtins.object"], "names": {".class": "SymbolTable", "__init__": {".class": "SymbolTableNode", "kind": "Mdef", "node": {".class": "FuncDef", "arg_kinds": [0, 0], "arg_names": ["self", "from_rule"], "flags": [], "fullname": "libcst._parser.parso.pgen2.grammar_parser.NFAState.__init__", "name": "__init__", "type": {".class": "CallableType", "arg_kinds": [0, 0], "arg_names": ["self", "from_rule"], "arg_types": ["libcst._parser.parso.pgen2.grammar_parser.NFAState", "builtins.str"], "bound_args": [], "def_extras": {"first_arg": "self"}, "fallback": "builtins.function", "from_concatenate": false, "implicit": false, "is_ellipsis_args": false, "name": "__init__ of NFAState", "ret_type": {".class": "NoneType"}, "type_guard": null, "variables": []}}}, "__repr__": {".class": "SymbolTableNode", "kind": "Mdef", "node": {".class": "FuncDef", "arg_kinds": [0], "arg_names": [null], "flags": [], "fullname": "libcst._parser.parso.pgen2.grammar_parser.NFAState.__repr__", "name": "__repr__", "type": {".class": "CallableType", "arg_kinds": [0], "arg_names": [null], "arg_types": ["libcst._parser.parso.pgen2.grammar_parser.NFAState"], "bound_args": [], "def_extras": {"first_arg": "self"}, "fallback": "builtins.function", "from_concatenate": false, "implicit": false, "is_ellipsis_args": false, "name": "__repr__ of NFAState", "ret_type": "builtins.str", "type_guard": null, "variables": []}}}, "add_arc": {".class": "SymbolTableNode", "kind": "Mdef", "node": {".class": "FuncDef", "arg_kinds": [0, 0, 1], "arg_names": ["self", "next_", "nonterminal_or_string"], "flags": [], "fullname": "libcst._parser.parso.pgen2.grammar_parser.NFAState.add_arc", "name": "add_arc", "type": {".class": "CallableType", "arg_kinds": [0, 0, 1], "arg_names": ["self", "next_", "nonterminal_or_string"], "arg_types": ["libcst._parser.parso.pgen2.grammar_parser.NFAState", "libcst._parser.parso.pgen2.grammar_parser.NFAState", {".class": "UnionType", "items": ["builtins.str", {".class": "NoneType"}]}], "bound_args": [], "def_extras": {"first_arg": "self"}, "fallback": "builtins.function", "from_concatenate": false, "implicit": false, "is_ellipsis_args": false, "name": "add_arc of NFAState", "ret_type": {".class": "NoneType"}, "type_guard": null, "variables": []}}}, "arcs": {".class": "SymbolTableNode", "implicit": true, "kind": "Mdef", "node": {".class": "Var", "flags": ["explicit_self_type", "is_ready"], "fullname": "libcst._parser.parso.pgen2.grammar_parser.NFAState.arcs", "name": "arcs", "type": {".class": "Instance", "args": ["libcst._parser.parso.pgen2.grammar_parser.NFAArc"], "type_ref": "builtins.list"}}}, "from_rule": {".class": "SymbolTableNode", "implicit": true, "kind": "Mdef", "node": {".class": "Var", "flags": [], "fullname": "libcst._parser.parso.pgen2.grammar_parser.NFAState.from_rule", "name": "from_rule", "type": "builtins.str"}}}, "slots": null, "tuple_type": null, "type_vars": [], "typeddict_type": null}}, "Optional": {".class": "SymbolTableNode", "cross_ref": "typing.Optional", "kind": "Gdef"}, "PythonTokenTypes": {".class": "SymbolTableNode", "cross_ref": "libcst._parser.parso.python.token.PythonTokenTypes", "kind": "Gdef"}, "Tuple": {".class": "SymbolTableNode", "cross_ref": "typing.Tuple", "kind": "Gdef"}, "__annotations__": {".class": "SymbolTableNode", "kind": "Gdef", "node": {".class": "Var", "flags": ["is_ready"], "fullname": "libcst._parser.parso.pgen2.grammar_parser.__annotations__", "name": "__annotations__", "type": {".class": "Instance", "args": ["builtins.str", {".class": "AnyType", "missing_import_name": null, "source_any": null, "type_of_any": 6}], "type_ref": "builtins.dict"}}}, "__doc__": {".class": "SymbolTableNode", "kind": "Gdef", "node": {".class": "Var", "flags": ["is_ready"], "fullname": "libcst._parser.parso.pgen2.grammar_parser.__doc__", "name": "__doc__", "type": "builtins.str"}}, "__file__": {".class": "SymbolTableNode", "kind": "Gdef", "node": {".class": "Var", "flags": ["is_ready"], "fullname": "libcst._parser.parso.pgen2.grammar_parser.__file__", "name": "__file__", "type": "builtins.str"}}, "__name__": {".class": "SymbolTableNode", "kind": "Gdef", "node": {".class": "Var", "flags": ["is_ready"], "fullname": "libcst._parser.parso.pgen2.grammar_parser.__name__", "name": "__name__", "type": "builtins.str"}}, "__package__": {".class": "SymbolTableNode", "kind": "Gdef", "node": {".class": "Var", "flags": ["is_ready"], "fullname": "libcst._parser.parso.pgen2.grammar_parser.__package__", "name": "__package__", "type": "builtins.str"}}, "parse_version_string": {".class": "SymbolTableNode", "cross_ref": "libcst._parser.parso.utils.parse_version_string", "kind": "Gdef"}, "tokenize": {".class": "SymbolTableNode", "cross_ref": "libcst._parser.parso.python.tokenize.tokenize", "kind": "Gdef"}}, "path": "/Users/christopherdecarolis/.pyenv/versions/3.8.6/envs/internal-workenv-3.8.6/lib/python3.8/site-packages/libcst/_parser/parso/pgen2/grammar_parser.py"}